jtmv/__init__.py
jtmv/jtmv.py
jtmv-0.1.2.dist-info/licenses/LICENSE
jtmv-0.1.2.dist-info/METADATA
jtmv-0.1.2.dist-info/WHEEL
jtmv-0.1.2.dist-info/entry_points.txt
jtmv-0.1.2.dist-info/top_level.txt
jtmv-0.1.2.dist-info/RECORD
