Metadata-Version: 2.4
Name: jtmv
Version: 0.1.2
Summary: Rename jupytext paired files while maintaining sync.
Author: Luke Smith
Project-URL: Homepage, https://github.com/lukeSmth/jtmv
Project-URL: Repository, https://github.com/lukeSmth/jtmv
Project-URL: Issues, https://github.com/lukeSmth/jtmv/issues
Keywords: jupyter,jupytext,notebook,rename,git
Requires-Python: >=3.7
License-File: LICENSE
Requires-Dist: jupytext>=1.14.0
Provides-Extra: dev
Requires-Dist: build; extra == "dev"
Requires-Dist: pytest; extra == "dev"
Requires-Dist: twine; extra == "dev"
Dynamic: license-file
